bw_data_usage_api_services/__init__.py
bw_data_usage_api_services/bw_api_secrets.py
bw_data_usage_api_services/bw_api_service_SGSingtelM2M.py
bw_data_usage_api_services/bw_api_service_kpn.py
bw_data_usage_api_services/bw_data_usage_providers.py
bw_data_usage_api_services/bw_object_factory.py
bw_data_usage_storage_utils/__init__.py
bw_data_usage_storage_utils/bw_storage_utils.py
bw_data_usage_storage_utils/bw_usage_queue_utils.py
bw_data_usage_storage_utils/bw_usage_table_utils.py
bwdatausagelib-0.0.5.dist-info/LICENSE
bwdatausagelib-0.0.5.dist-info/METADATA
bwdatausagelib-0.0.5.dist-info/WHEEL
bwdatausagelib-0.0.5.dist-info/top_level.txt
bwdatausagelib-0.0.5.dist-info/RECORD
