Metadata-Version: 2.1
Name: bwdatausagelib
Version: 0.0.5
Summary: A packaged library for sim usage data
Home-page: https://github.com/ZainBW/bwdatausagelib
Author: Mohamad Zain Bin Aziz
Author-email: mohamad.zain@bluewireless.com
License: UNKNOWN
Project-URL: Bug Tracker, https://github.com/ZainBW/bwdatausage/issues
Platform: UNKNOWN
Classifier: Programming Language :: Python :: 3
Classifier: License :: OSI Approved :: MIT License
Classifier: Operating System :: OS Independent
Requires-Python: >=3.8
License-File: LICENSE
Requires-Dist: azure.keyvault.secrets
Requires-Dist: azure-cosmosdb-table
Requires-Dist: azure.storage.queue
Requires-Dist: azure.identity
Requires-Dist: requests
